_oalib.pyd
oalib.py
oapackage/__init__.py
oapackage/_scanf.py
oapackage/conference.py
oapackage/Doptim.py
oapackage/graphtools.py
oapackage/markup.py
oapackage/oahelper.py
oapackage/scanf.py
oapackage-2.7.20.dist-info/METADATA
oapackage-2.7.20.dist-info/WHEEL
oapackage-2.7.20.dist-info/licenses/LICENSE
oapackage-2.7.20.dist-info/RECORD
