Metadata-Version: 2.4
Name: oapackage
Version: 2.7.20
Summary: Package to generate and analyse orthogonal arrays, conference designs and optimal designs
Keywords: orthogonal arrays,design of experiments,conference designs,isomorphism testing
Author-Email: Pieter Eendebak <pieter.eendebak@gmail.com>
License-Expression: BSD-3-Clause
Classifier: Development Status :: 4 - Beta
Classifier: Intended Audience :: Science/Research
Classifier: Programming Language :: Python :: 3
Classifier: Programming Language :: Python :: 3.10
Classifier: Programming Language :: Python :: 3.11
Classifier: Programming Language :: Python :: 3.12
Classifier: Programming Language :: Python :: 3.13
Classifier: Programming Language :: Python :: 3.14
Project-URL: Homepage, http://www.pietereendebak.nl/oapackage/index.html
Project-URL: Repository, https://github.com/eendebakpt/oapackage
Requires-Python: >=3.10
Requires-Dist: numpy>=2.0
Requires-Dist: python-dateutil
Requires-Dist: matplotlib
Provides-Extra: test
Requires-Dist: pytest; extra == "test"
Requires-Dist: coverage; extra == "test"
Requires-Dist: mock; extra == "test"
Provides-Extra: doc
Requires-Dist: sphinx; extra == "doc"
Requires-Dist: sphinxcontrib-bibtex; extra == "doc"
Requires-Dist: sphinxcontrib-napoleon; extra == "doc"
Requires-Dist: breathe; extra == "doc"
